cnl/__init__.py
cnl/cnl_run.py
cnl/config_processing.py
cnl/types/Config.py
cnl/types/__init__.py
cnl_cli/__init__.py
cnl_cli/main.py
cnl_deployment_targets/__init__.py
cnl_deployment_targets/telegram/__init__.py
cnl_deployment_targets/telegram/config.py
cnl_deployment_targets/telegram/main.py
cnl_deployment_targets/telegram/test_from_tg_to_engine.py
cnl_deployment_targets/telegram/types.py
cnl_deployment_targets/telegram/operations/__init__.py
cnl_deployment_targets/telegram/operations/engine.py
cnl_deployment_targets/telegram/operations/engine_types.py
cnl_deployment_targets/telegram/operations/tg.py
cnl_deployment_targets/telegram/operations/tg_schemas.py
cnl_engine/__init__.py
cnl_engine/cnl_engine_api_app_runner.py
cnl_engine/config.py
cnl_engine/main.py
cnl_engine/periodic_engine_manager.py
cnl_engine/api/__init__.py
cnl_engine/api/app.py
cnl_engine/api/controllers.py
cnl_engine/api/schemas.py
cnl_engine/db/__init__.py
cnl_engine/db/engine_session.py
cnl_engine/db/db_management/__init__.py
cnl_engine/db/db_management/create_tables.py
cnl_engine/db/models/__init__.py
cnl_engine/db/models/_base.py
cnl_engine/db/models/cnl_store.py
cnl_engine/db/models/conversation_history.py
cnl_engine/db/models/conversation_meta.py
cnl_engine/db/models/new_events_engine_management.py
cnl_engine/db/repositories/__init__.py
cnl_engine/db/repositories/cnl_store.py
cnl_engine/db/repositories/conversation_history.py
cnl_engine/db/repositories/conversation_meta.py
cnl_engine/db/repositories/new_events_engine_management.py
cnl_engine/services/__init__.py
cnl_engine/services/conversation_history_manipulator.py
cnl_engine/services/engine_actions.py
cnl_engine/services/events_from_front_handler.py
cnl_engine/services/greeter.py
cnl_engine/services/engine_related/__init__.py
cnl_engine/services/engine_related/engine_related.py
cnl_engine/services/engine_related/user_function_process_wrapper.py
cnl_engine/types/__init__.py
cnl_engine/types/common_types.py
cnl_engine/utils/__init__.py
cnl-0.1.21.dist-info/METADATA
cnl-0.1.21.dist-info/WHEEL
cnl-0.1.21.dist-info/entry_points.txt
cnl-0.1.21.dist-info/top_level.txt
cnl-0.1.21.dist-info/RECORD
