Metadata-Version: 2.1
Name: cnl
Version: 0.1.21
Home-page: 
Requires-Dist: fastapi
Requires-Dist: uvicorn
Requires-Dist: typer[all]
Requires-Dist: SQLAlchemy
Requires-Dist: httpx
